voidray/__init__.py
voidray/__version__.py
voidray/animation/__init__.py
voidray/animation/animation_manager.py
voidray/animation/tween.py
voidray/assets/__init__.py
voidray/assets/asset_loader.py
voidray/audio/__init__.py
voidray/audio/audio_effects.py
voidray/audio/audio_manager.py
voidray/audio/spatial_audio.py
voidray/core/__init__.py
voidray/core/asset_streaming.py
voidray/core/compatibility.py
voidray/core/component.py
voidray/core/component_registry.py
voidray/core/config.py
voidray/core/debug_overlay.py
voidray/core/engine.py
voidray/core/engine_state.py
voidray/core/engine_validator.py
voidray/core/error_dialog.py
voidray/core/event_system.py
voidray/core/game_object.py
voidray/core/logger.py
voidray/core/node_system.py
voidray/core/profiler.py
voidray/core/resource_manager.py
voidray/core/resource_pool.py
voidray/core/scene.py
voidray/core/scene_manager.py
voidray/core/scene_transitions.py
voidray/core/world_manager.py
voidray/effects/__init__.py
voidray/effects/particle_system.py
voidray/effects/post_processing.py
voidray/graphics/__init__.py
voidray/graphics/camera.py
voidray/graphics/renderer.py
voidray/graphics/sprite.py
voidray/input/__init__.py
voidray/input/input_manager.py
voidray/lighting/__init__.py
voidray/lighting/lighting_system.py
voidray/math/__init__.py
voidray/math/transform.py
voidray/math/vector2.py
voidray/networking/__init__.py
voidray/networking/message_system.py
voidray/networking/multiplayer_manager.py
voidray/networking/network_manager.py
voidray/physics/__init__.py
voidray/physics/collider.py
voidray/physics/collision.py
voidray/physics/physics_engine.py
voidray/physics/physics_system.py
voidray/physics/quadtree.py
voidray/physics/rigidbody.py
voidray/rendering/__init__.py
voidray/rendering/camera.py
voidray/rendering/renderer.py
voidray/rendering/shader_manager.py
voidray/rendering/sprite.py
voidray/scripting/__init__.py
voidray/scripting/script_component.py
voidray/scripting/script_manager.py
voidray/tilemap/__init__.py
voidray-3.1.0.dist-info/licenses/LICENSE
voidray-3.1.0.dist-info/licenses/LICENSE_ENGINE_USE.md
voidray-3.1.0.dist-info/METADATA
voidray-3.1.0.dist-info/WHEEL
voidray-3.1.0.dist-info/entry_points.txt
voidray-3.1.0.dist-info/top_level.txt
voidray-3.1.0.dist-info/RECORD
