Metadata-Version: 2.4
Name: voidray
Version: 3.1.0
Summary: Professional 2D/2.5D Game Engine for Python
Home-page: https://github.com/voidray/voidray
Author: VoidRay Team
Author-email: VoidRay Team <info@voidray.dev>
Maintainer-email: VoidRay Team <info@voidray.dev>
License: GPL-3.0
Project-URL: Homepage, https://github.com/voidray/voidray
Project-URL: Documentation, https://voidray.readthedocs.io/
Project-URL: Repository, https://github.com/voidray/voidray
Project-URL: Bug Tracker, https://github.com/voidray/voidray/issues
Keywords: game,engine,pygame,2d,2.5d,games,development
Classifier: Development Status :: 5 - Production/Stable
Classifier: Intended Audience :: Developers
Classifier: Topic :: Games/Entertainment
Classifier: Topic :: Software Development :: Libraries :: pygame
Classifier: License :: OSI Approved :: GNU General Public License v3 (GPLv3)
Classifier: Programming Language :: Python :: 3
Classifier: Programming Language :: Python :: 3.8
Classifier: Programming Language :: Python :: 3.9
Classifier: Programming Language :: Python :: 3.10
Classifier: Programming Language :: Python :: 3.11
Classifier: Programming Language :: Python :: 3.12
Classifier: Operating System :: OS Independent
Requires-Python: >=3.8
License-File: LICENSE
License-File: LICENSE_ENGINE_USE.md
Requires-Dist: pygame>=2.1.0
Requires-Dist: numpy>=1.21.0
Requires-Dist: pillow>=8.0.0
Provides-Extra: dev
Requires-Dist: pytest>=6.0; extra == "dev"
Requires-Dist: pytest-cov; extra == "dev"
Requires-Dist: black; extra == "dev"
Requires-Dist: flake8; extra == "dev"
Provides-Extra: networking
Requires-Dist: websockets>=10.0; extra == "networking"
Provides-Extra: audio
Requires-Dist: pydub>=0.25.0; extra == "audio"
Dynamic: author
Dynamic: home-page
Dynamic: license-file
Dynamic: requires-python
